laneful/__init__.py
laneful/async_client.py
laneful/base.py
laneful/client.py
laneful/exceptions.py
laneful/models.py
laneful/webhooks.py
laneful-1.0.6.dist-info/METADATA
laneful-1.0.6.dist-info/WHEEL
laneful-1.0.6.dist-info/licenses/LICENSE
laneful-1.0.6.dist-info/RECORD
