Metadata-Version: 2.4
Name: laneful
Version: 1.0.6
Summary: Python client library for the Laneful API
Project-URL: Homepage, https://github.com/lanefulhq/laneful-python
Project-URL: Repository, https://github.com/lanefulhq/laneful-python
Project-URL: Documentation, https://github.com/lanefulhq/laneful-python#readme
Project-URL: Bug Tracker, https://github.com/lanefulhq/laneful-python/issues
Author-email: Laneful <support@laneful.com>
License: MIT
License-File: LICENSE
Keywords: api,client,email,laneful
Classifier: Development Status :: 5 - Production/Stable
Classifier: Intended Audience :: Developers
Classifier: License :: OSI Approved :: MIT License
Classifier: Programming Language :: Python :: 3
Classifier: Programming Language :: Python :: 3.9
Classifier: Programming Language :: Python :: 3.10
Classifier: Programming Language :: Python :: 3.11
Classifier: Programming Language :: Python :: 3.12
Classifier: Programming Language :: Python :: 3.13
Classifier: Topic :: Communications :: Email
Classifier: Topic :: Software Development :: Libraries :: Python Modules
Requires-Python: >=3.9
Requires-Dist: aiohttp>=3.8.0
Requires-Dist: requests>=2.28.0
Provides-Extra: all
Requires-Dist: aiohttp>=3.8.0; extra == 'all'
Requires-Dist: requests>=2.28.0; extra == 'all'
Provides-Extra: async
Requires-Dist: aiohttp>=3.8.0; extra == 'async'
Provides-Extra: async-only
Requires-Dist: aiohttp>=3.8.0; extra == 'async-only'
Provides-Extra: dev
Requires-Dist: aiohttp>=3.8.0; extra == 'dev'
Requires-Dist: black>=22.0.0; extra == 'dev'
Requires-Dist: isort>=5.10.0; extra == 'dev'
Requires-Dist: mypy>=1.0.0; extra == 'dev'
Requires-Dist: pytest-asyncio>=0.24.0; extra == 'dev'
Requires-Dist: pytest-cov>=4.0.0; extra == 'dev'
Requires-Dist: pytest>=8.3.5; extra == 'dev'
Requires-Dist: requests>=2.28.0; extra == 'dev'
Requires-Dist: ruff>=0.1.0; extra == 'dev'
Provides-Extra: sync
Requires-Dist: requests>=2.28.0; extra == 'sync'
